fedmsg_migration_tools/__init__.py
fedmsg_migration_tools/bridges.py
fedmsg_migration_tools/cli.py
fedmsg_migration_tools/config.py
fedmsg_migration_tools/verify_missing.py
fedmsg_migration_tools/tests/__init__.py
fedmsg_migration_tools/tests/test_bridges.py
fedmsg_migration_tools/tests/fixtures/fedmsg.crt
fedmsg_migration_tools/tests/fixtures/fedmsg.key
fedmsg_migration_tools-0.1.2.dist-info/METADATA
fedmsg_migration_tools-0.1.2.dist-info/RECORD
fedmsg_migration_tools-0.1.2.dist-info/WHEEL
fedmsg_migration_tools-0.1.2.dist-info/entry_points.txt
fedmsg_migration_tools-0.1.2.dist-info/top_level.txt
