Metadata-Version: 2.1
Name: fedmsg-migration-tools
Version: 0.1.2
Summary: A set of tools to aid in migrating from fedmsg to AMQP.
Home-page: https://github.com/fedora-infra/fedmsg-migration-tools
Maintainer: Fedora Infrastructure Team
Maintainer-email: infrastructure@lists.fedoraproject.org
License: GPLv2+
Keywords: fedora
Platform: Fedora
Platform: GNU/Linux
Classifier: Development Status :: 4 - Beta
Classifier: License :: OSI Approved :: GNU General Public License v2 or later (GPLv2+)
Classifier: Operating System :: POSIX :: Linux
Classifier: Programming Language :: Python :: 3
Requires-Dist: click
Requires-Dist: fedmsg[crypto_ng]
Requires-Dist: twisted
Requires-Dist: txzmq
Requires-Dist: fedora-messaging
Requires-Dist: pytoml
